src/adzone_smart_ads/__init__.py
src/adzone_smart_ads/ai_calculator.py
src/adzone_smart_ads/main.py
packaging_adzone-0.0.1.dist-info/METADATA
packaging_adzone-0.0.1.dist-info/WHEEL
packaging_adzone-0.0.1.dist-info/licenses/LICENSE
packaging_adzone-0.0.1.dist-info/RECORD
